ai_text_humanizer/__init__.py
ai_text_humanizer/cli.py
ai_text_humanizer/core.py
app/__init__.py
app/app.py
app/fa_combo.py
app/fa_hazm.py
app/fa_stanza.py
ai_text_humanizer-1.0.0.dist-info/LICENSE
ai_text_humanizer-1.0.0.dist-info/METADATA
ai_text_humanizer-1.0.0.dist-info/WHEEL
ai_text_humanizer-1.0.0.dist-info/entry_points.txt
ai_text_humanizer-1.0.0.dist-info/top_level.txt
ai_text_humanizer-1.0.0.dist-info/RECORD
