Metadata-Version: 2.1
Name: ai-text-humanizer
Version: 1.0.0
Summary: AI-powered text humanizer for English and Persian (فارسی)
Home-page: https://github.com/mohammadham/AI-Text-Humanizer
Author: Your Name
Author-email: your@email.com
Classifier: Programming Language :: Python :: 3
Classifier: License :: OSI Approved :: MIT License
Classifier: Operating System :: OS Independent
Classifier: Natural Language :: English
Classifier: Natural Language :: Persian
Requires-Python: >=3.7
License-File: LICENSE
Requires-Dist: streamlit
Requires-Dist: spacy
Requires-Dist: nltk
Requires-Dist: sentence-transformers
Requires-Dist: hazm
Requires-Dist: stanza
Requires-Dist: transformers
